{"external_url":"https://fullhd-wallpapers-brinis.blogspot.com/","properties":{"Background":"purple background","Ghuthra":"Golden","Hat":"christmas hat","Necklace":"Diamond  nicklace","Thobe":"Red Black lines","Igal":"Green"},"name":"Pixel Art Arab Man #687","description":"a collection contains a limited edition of Arab Man pixel art, limited to 10k images.  _purple background_Golden_christmas hat_Diamond  nicklace_Red Black lines_Green","image":"https://raw.githubusercontent.com/GamingPromotions/picHost/main/ArabMan/images/345.jpg","attributes":null}
